pynecone/.templates/app/__init__.py
pynecone/.templates/app/tutorial.py
pynecone/.templates/assets/favicon.ico
pynecone/.templates/web/.gitignore
pynecone/.templates/web/bun.lockb
pynecone/.templates/web/next.config.js
pynecone/.templates/web/package.json
pynecone/.templates/web/pages/404.js
pynecone/.templates/web/pages/_app.js
pynecone/.templates/web/pcversion.txt
pynecone/.templates/web/styles/code/prism.js
pynecone/.templates/web/utils/state.js
pynecone/__init__.py
pynecone/app.py
pynecone/base.py
pynecone/compiler/__init__.py
pynecone/compiler/compiler.py
pynecone/compiler/templates.py
pynecone/compiler/utils.py
pynecone/components/__init__.py
pynecone/components/base/__init__.py
pynecone/components/base/bare.py
pynecone/components/base/body.py
pynecone/components/base/document.py
pynecone/components/base/head.py
pynecone/components/base/link.py
pynecone/components/base/meta.py
pynecone/components/component.py
pynecone/components/datadisplay/__init__.py
pynecone/components/datadisplay/badge.py
pynecone/components/datadisplay/code.py
pynecone/components/datadisplay/datatable.py
pynecone/components/datadisplay/divider.py
pynecone/components/datadisplay/list.py
pynecone/components/datadisplay/stat.py
pynecone/components/datadisplay/table.py
pynecone/components/disclosure/__init__.py
pynecone/components/disclosure/accordion.py
pynecone/components/disclosure/tabs.py
pynecone/components/disclosure/visuallyhidden.py
pynecone/components/feedback/__init__.py
pynecone/components/feedback/alert.py
pynecone/components/feedback/circularprogress.py
pynecone/components/feedback/progress.py
pynecone/components/feedback/skeleton.py
pynecone/components/feedback/spinner.py
pynecone/components/forms/__init__.py
pynecone/components/forms/button.py
pynecone/components/forms/checkbox.py
pynecone/components/forms/copytoclipboard.py
pynecone/components/forms/editable.py
pynecone/components/forms/formcontrol.py
pynecone/components/forms/iconbutton.py
pynecone/components/forms/input.py
pynecone_io-0.1.14.dist-info/LICENSE
pynecone_io-0.1.14.dist-info/WHEEL
pynecone_io-0.1.14.dist-info/entry_points.txt
pynecone_io-0.1.14.dist-info/METADATA
pynecone_io-0.1.14.dist-info/RECORD
